playwright_project/__init__.py
playwright_project-0.0.5.dist-info/entry_points.txt
playwright_project-0.0.5.dist-info/LICENSE
playwright_project-0.0.5.dist-info/METADATA
playwright_project-0.0.5.dist-info/WHEEL
playwright_project-0.0.5.dist-info/RECORD
