Metadata-Version: 2.1
Name: playwright-project
Version: 0.0.5
Summary: After this course i will be a decent playwright and pytest developer
License: MIT
Author: Jean Kobeis
Author-email: johnny_kobeis@live.com
Requires-Python: >=3.11,<=3.11.6
Classifier: License :: OSI Approved :: MIT License
Classifier: Programming Language :: Python :: 3
Classifier: Programming Language :: Python :: 3.11
Requires-Dist: cisco-sdwan (>=1.21.3,<2.0.0)
Requires-Dist: playwright (>=1.38.0,<2.0.0)
Project-URL: Bug Tracker, https://github.com/jeankobeis/playwrights/issues
Project-URL: Home Page, https://github.com/jeankobeis/playwrights
